mcaption/__init__.py
mcaption/main.py
mcaption/utils.py
mcaption-0.0.6.dist-info/LICENSE
mcaption-0.0.6.dist-info/METADATA
mcaption-0.0.6.dist-info/WHEEL
mcaption-0.0.6.dist-info/top_level.txt
mcaption-0.0.6.dist-info/RECORD
