Metadata-Version: 2.1
Name: mcaption
Version: 0.0.6
Summary: A modern implementation of simple image captioning
Home-page: https://github.com/manbehindthemadness/modern-caption
Author: Manbehindthemadness
Author-email: manbehindthemadness@gmail.com
Classifier: Programming Language :: Python :: 3
Classifier: License :: OSI Approved :: MIT License
Classifier: Operating System :: OS Independent
Requires-Python: >=3.10
License-File: LICENSE
Requires-Dist: scikit-image >=0.18.1
Requires-Dist: transformers >=4.10.2
Requires-Dist: numpy
Requires-Dist: ftfy
Requires-Dist: tqdm
Requires-Dist: torch >=2.0.0
Requires-Dist: torchvision >=0.17.0
Requires-Dist: quickdl
